blackdogosint/README.rst
blackdogosint/__init__.py
blackdogosint/mods/Archives/__init__.py
blackdogosint/mods/Business_Records/__init__.py
blackdogosint/mods/Classifieds/__init__.py
blackdogosint/mods/Dark_Web/__init__.py
blackdogosint/mods/Dating/__init__.py
blackdogosint/mods/Digital_Currency/__init__.py
blackdogosint/mods/Documentation/__init__.py
blackdogosint/mods/Domain_Name/__init__.py
blackdogosint/mods/Email_Address/__init__.py
blackdogosint/mods/Encoding_Decoding/__init__.py
blackdogosint/mods/Exploits_e_Advisories/__init__.py
blackdogosint/mods/Forum_Blog_IRC/__init__.py
blackdogosint/mods/Geolocation_Tool_Maps/__init__.py
blackdogosint/mods/IP_Address/Geolocation/__init__.py
blackdogosint/mods/IP_Address/Geolocation/ipverse.py
blackdogosint/mods/IP_Address/HostPortDiscovery/__init__.py
blackdogosint/mods/IP_Address/HostPortDiscovery/shodansearch.py
blackdogosint/mods/IP_Address/__init__.py
blackdogosint/mods/Image_Video_Docs/__init__.py
blackdogosint/mods/Instant_Messaging/__init__.py
blackdogosint/mods/Language_Translation/__init__.py
blackdogosint/mods/Malicious_File_Analysis/__init__.py
blackdogosint/mods/Metadata/__init__.py
blackdogosint/mods/Mobile_Emulation/__init__.py
blackdogosint/mods/OpSec/__init__.py
blackdogosint/mods/People_Search_Engines/__init__.py
blackdogosint/mods/Public_Records/__init__.py
blackdogosint/mods/ScreenShot/Screenshot.py
blackdogosint/mods/ScreenShot/__init__.py
blackdogosint/mods/Search/__init__.py
blackdogosint/mods/Search/discovery/__init__.py
blackdogosint/mods/Search/discovery/anubis.py
blackdogosint/mods/Search/discovery/baidusearch.py
blackdogosint/mods/Search/discovery/binaryedgesearch.py
blackdogosint/mods/Search/discovery/bingsearch.py
blackdogosint/mods/Search/discovery/bufferoverun.py
blackdogosint/mods/Search/discovery/censysearch.py
blackdogosint/mods/Search/discovery/certspottersearch.py
blackdogosint/mods/Search/discovery/crtsh.py
blackdogosint/mods/Search/discovery/dnsdumpster.py
blackdogosint-0.1.42.dist-info/LICENSE
blackdogosint-0.1.42.dist-info/WHEEL
blackdogosint-0.1.42.dist-info/METADATA
blackdogosint-0.1.42.dist-info/RECORD
